ariadne_auth/__about__.py
ariadne_auth/__init__.py
ariadne_auth/authz.py
ariadne_auth/exceptions.py
ariadne_auth/types.py
ariadne_auth-0.1.1.dist-info/METADATA
ariadne_auth-0.1.1.dist-info/WHEEL
ariadne_auth-0.1.1.dist-info/licenses/LICENSE.txt
ariadne_auth-0.1.1.dist-info/RECORD
