Metadata-Version: 2.4
Name: ariadne-auth
Version: 0.1.1
Summary: An Ariadne extension for authorization, allowing global permissions for all resolvers and fine-grained control over required permissions for specific resolvers in GraphQL APIs.
Project-URL: Homepage, https://github.com/mirumee/ariadne-auth
Project-URL: Issues, https://github.com/mirumee/ariadne-auth/issues
Author-email: Mirumee Labs <hello@mirumee.com>
License-Expression: BSD-3-Clause
License-File: LICENSE.txt
Keywords: ariadne,ariadne-extension,authorization,permissions
Classifier: Development Status :: 4 - Beta
Classifier: Programming Language :: Python
Classifier: Programming Language :: Python :: 3.9
Classifier: Programming Language :: Python :: 3.10
Classifier: Programming Language :: Python :: 3.11
Classifier: Programming Language :: Python :: 3.12
Classifier: Programming Language :: Python :: 3.13
Requires-Python: >=3.9
Requires-Dist: ariadne
Requires-Dist: typing-extensions
Provides-Extra: dev
Requires-Dist: ipdb; extra == 'dev'
Requires-Dist: rich; extra == 'dev'
Requires-Dist: starlette; extra == 'dev'
Requires-Dist: uvicorn; extra == 'dev'
Provides-Extra: types
Requires-Dist: mypy>=1.0.0; extra == 'types'
